LICENSE
Makefile
README.rst
VERSION
sage_version.py
setup.py
docs/Makefile
docs/source/conf.py
docs/source/deformation.rst
docs/source/index.rst
pydeformation/__init__.py
pydeformation/deformation.pxd
pydeformation/deformation.pyx
pydeformation.egg-info/PKG-INFO
pydeformation.egg-info/SOURCES.txt
pydeformation.egg-info/dependency_links.txt
pydeformation.egg-info/requires.txt
pydeformation.egg-info/top_level.txt